datasheet/__init__.py
datasheet/html_renderer.py
datasheet/sheet.py
datasheet/types.py
datasheet/data/__init__.py
datasheet/data/collapse.js
datasheet/data/default.css
datasheet/data/pathfinder.css
datasheet-1.2.3.dist-info/LICENSE
datasheet-1.2.3.dist-info/WHEEL
datasheet-1.2.3.dist-info/METADATA
datasheet-1.2.3.dist-info/RECORD
