Metadata-Version: 2.1
Name: datasheet
Version: 1.2.3
Summary: A library to generate HTML pages containing all sorts of output
Home-page: https://github.com/KnorrFG/datasheet
Author: Felix G. Knorr
Author-email: knorr.felix@gmx.de
Classifier: License :: OSI Approved :: MIT License
Requires-Dist: markdown
Requires-Dist: pandas
Requires-Dist: yattag
Requires-Dist: matplotlib
Requires-Dist: jum
Requires-Dist: Jinja2
